pyvider/__init__.py
pyvider/hcl/__init__.py
pyvider/hcl/_version.py
pyvider/hcl/exceptions.py
pyvider/hcl/factories.py
pyvider/hcl/parser.py
pyvider/hcl/printer.py
pyvider/hcl/terraform.py
pyvider_hcl-0.0.1000.dist-info/licenses/LICENSE
pyvider_hcl-0.0.1000.dist-info/METADATA
pyvider_hcl-0.0.1000.dist-info/WHEEL
pyvider_hcl-0.0.1000.dist-info/top_level.txt
pyvider_hcl-0.0.1000.dist-info/RECORD
