Metadata-Version: 2.4
Name: pyvider-hcl
Version: 0.0.1000
Summary: Pyvider HCL: A wrapper for python-hcl2 integrating with Pyvider's Cty type system.
Author-email: Tim Perkins <code@tim.life>
Maintainer-email: "provide.io" <code@provide.io>
License-Expression: Apache-2.0
Classifier: Development Status :: 3 - Alpha
Classifier: Intended Audience :: Developers
Classifier: Operating System :: OS Independent
Classifier: Programming Language :: Python :: 3
Classifier: Programming Language :: Python :: 3.11
Classifier: Programming Language :: Python :: 3.12
Classifier: Programming Language :: Python :: 3.13
Classifier: Typing :: Typed
Requires-Python: >=3.11
License-File: LICENSE
Requires-Dist: attrs>=25.3.0
Requires-Dist: python-hcl2>=7.2.1
Requires-Dist: pyvider>=0.0.0.post0
Requires-Dist: pyvider-cty>=0.0.113
Requires-Dist: provide-foundation>=0.0.0
Requires-Dist: regex>=2024.11.6
Dynamic: license-file
